.dockerignore
.gitignore
.gitlab-ci.yml
.readthedocs.yml
AUTHORS.rst
Contributing.rst
LICENSE.txt
README.rst
requirements.txt
setup.py
test-environment.yml
tox.ini
.github/workflows/publish.yml
.github/workflows/test.yml
binder/postBuild
bluegraph/__init__.py
bluegraph/exceptions.py
bluegraph/version.py
bluegraph.egg-info/PKG-INFO
bluegraph.egg-info/SOURCES.txt
bluegraph.egg-info/dependency_links.txt
bluegraph.egg-info/requires.txt
bluegraph.egg-info/top_level.txt
bluegraph/backends/__init__.py
bluegraph/backends/configs.py
bluegraph/backends/params.py
bluegraph/backends/utils.py
bluegraph/backends/gensim/__init__.py
bluegraph/backends/gensim/embed/__init__.py
bluegraph/backends/gensim/embed/embedders.py
bluegraph/backends/graph_tool/__init__.py
bluegraph/backends/graph_tool/io.py
bluegraph/backends/graph_tool/analyse/__init__.py
bluegraph/backends/graph_tool/analyse/communities.py
bluegraph/backends/graph_tool/analyse/metrics.py
bluegraph/backends/graph_tool/analyse/paths.py
bluegraph/backends/neo4j/__init__.py
bluegraph/backends/neo4j/io.py
bluegraph/backends/neo4j/analyse/__init__.py
bluegraph/backends/neo4j/analyse/communities.py
bluegraph/backends/neo4j/analyse/metrics.py
bluegraph/backends/neo4j/analyse/paths.py
bluegraph/backends/neo4j/embed/__init__.py
bluegraph/backends/neo4j/embed/embedders.py
bluegraph/backends/networkx/__init__.py
bluegraph/backends/networkx/io.py
bluegraph/backends/networkx/analyse/__init__.py
bluegraph/backends/networkx/analyse/communities.py
bluegraph/backends/networkx/analyse/metrics.py
bluegraph/backends/networkx/analyse/paths.py
bluegraph/backends/stellargraph/__init__.py
bluegraph/backends/stellargraph/io.py
bluegraph/backends/stellargraph/embed/__init__.py
bluegraph/backends/stellargraph/embed/embedders.py
bluegraph/backends/stellargraph/embed/ml_utils.py
bluegraph/core/__init__.py
bluegraph/core/io.py
bluegraph/core/utils.py
bluegraph/core/analyse/__init__.py
bluegraph/core/analyse/communities.py
bluegraph/core/analyse/metrics.py
bluegraph/core/analyse/paths.py
bluegraph/core/embed/__init__.py
bluegraph/core/embed/embedders.py
bluegraph/downstream/__init__.py
