Metadata-Version: 2.1
Name: bluegraph
Version: 0.1.6
Summary: Knowledge Graphs analytics.
Home-page: https://github.com/BlueBrain/BlueGraph
Author: Blue Brain Project, EPFL
License: UNKNOWN
Keywords: framework knowledge graph data science
Platform: UNKNOWN
Classifier: Intended Audience :: Information Technology
Classifier: Intended Audience :: Science/Research
Classifier: Topic :: Scientific/Engineering
Classifier: Programming Language :: Python :: 3 :: Only
Classifier: Natural Language :: English
Requires-Python: >=3.7
Provides-Extra: dev
Provides-Extra: docs
Provides-Extra: cord19kg
Provides-Extra: neo4j
Provides-Extra: stellargraph
Provides-Extra: gensim
Provides-Extra: all
